napari_mousetumorpy/__init__.py
napari_mousetumorpy/_crop.py
napari_mousetumorpy/_picker.py
napari_mousetumorpy/_remove.py
napari_mousetumorpy/_table.py
napari_mousetumorpy/_tracks.py
napari_mousetumorpy/_version.py
napari_mousetumorpy/_widget.py
napari_mousetumorpy/napari.yaml
napari_mousetumorpy-0.0.3.dist-info/licenses/LICENSE
napari_mousetumorpy-0.0.3.dist-info/METADATA
napari_mousetumorpy-0.0.3.dist-info/WHEEL
napari_mousetumorpy-0.0.3.dist-info/entry_points.txt
napari_mousetumorpy-0.0.3.dist-info/top_level.txt
napari_mousetumorpy-0.0.3.dist-info/RECORD
