Metadata-Version: 2.4
Name: napari-mousetumorpy
Version: 0.0.3
Author-email: EPFL Center for Imaging <imaging@epfl.ch>
License: Copyright (c) 2024, EPFL
Project-URL: homepage, https://github.com/mousetumorpy/napari-mousetumorpy
Project-URL: repository, https://github.com/mousetumorpy/napari-mousetumorpy
Classifier: Development Status :: 2 - Pre-Alpha
Classifier: Intended Audience :: Developers
Classifier: License :: OSI Approved :: BSD License
Classifier: Operating System :: OS Independent
Classifier: Programming Language :: Python
Classifier: Programming Language :: Python :: 3
Classifier: Programming Language :: Python :: 3 :: Only
Classifier: Programming Language :: Python :: 3.9
Classifier: Programming Language :: Python :: 3.10
Classifier: Programming Language :: Python :: 3.11
Classifier: Programming Language :: Python :: 3.12
Classifier: Programming Language :: Python :: 3.13
Classifier: Topic :: Scientific/Engineering :: Image Processing
Requires-Python: >=3.9
License-File: LICENSE
Requires-Dist: numpy
Requires-Dist: pandas
Requires-Dist: tifffile
Requires-Dist: napari[all]
Requires-Dist: napari-toolkit
Requires-Dist: imaging-server-kit>=0.1.3
Requires-Dist: napari-serverkit>=0.1.2
Requires-Dist: mousetumorpy>=0.0.2
Dynamic: license-file
